sscstu/__init__.py
sscstu/transfer.py
sscstu/conversions/__init__.py
sscstu/core/__init__.py
sscstu/core/exceptions.py
sscstu/core/storage.py
sscstu/storage/__init__.py
sscstu/storage/local.py
sscstu/storage/s3.py
sscstu/storage/s3storage.py
sscstu/storage/storage.py
sscstu-0.0.3.dist-info/LICENSE
sscstu-0.0.3.dist-info/METADATA
sscstu-0.0.3.dist-info/WHEEL
sscstu-0.0.3.dist-info/top_level.txt
sscstu-0.0.3.dist-info/RECORD
